{
    "project": {
        "name": "eda.js",
        "description": "utilities",
        "url": "https://github.com/taikiken/eda.js"
    },
    "files": {
        "src/net/Cookie.js": {
            "name": "src/net/Cookie.js",
            "modules": {
                "Cookie": 1
            },
            "classes": {
                "Cookie": 1
            },
            "fors": {},
            "namespaces": {}
        },
        "src/net/Query.js": {
            "name": "src/net/Query.js",
            "modules": {
                "Query": 1
            },
            "classes": {
                "Query": 1
            },
            "fors": {},
            "namespaces": {}
        },
        "src/util/Kana.js": {
            "name": "src/util/Kana.js",
            "modules": {
                "Kana": 1
            },
            "classes": {
                "Kana": 1
            },
            "fors": {},
            "namespaces": {}
        },
        "src/util/List.js": {
            "name": "src/util/List.js",
            "modules": {},
            "classes": {
                "List": 1
            },
            "fors": {},
            "namespaces": {}
        },
        "src/util/Num.js": {
            "name": "src/util/Num.js",
            "modules": {
                "Num": 1
            },
            "classes": {
                "Num": 1
            },
            "fors": {},
            "namespaces": {}
        },
        "src/util/Str.js": {
            "name": "src/util/Str.js",
            "modules": {
                "Str": 1
            },
            "classes": {},
            "fors": {},
            "namespaces": {}
        },
        "src/util/Time.js": {
            "name": "src/util/Time.js",
            "modules": {
                "Time": 1
            },
            "classes": {
                "Time": 1
            },
            "fors": {},
            "namespaces": {}
        },
        "src/eda.js": {
            "name": "src/eda.js",
            "modules": {
                "Eda": 1
            },
            "classes": {},
            "fors": {},
            "namespaces": {}
        }
    },
    "modules": {
        "Eda": {
            "name": "Eda",
            "submodules": {
                "Cookie": 1,
                "Query": 1,
                "Kana": 1,
                "Num": 1,
                "Str": 1,
                "Time": 1
            },
            "elements": {},
            "classes": {
                "Cookie": 1,
                "Query": 1,
                "Kana": 1,
                "List": 1,
                "Num": 1,
                "Time": 1
            },
            "fors": {},
            "namespaces": {},
            "tag": "module",
            "file": "src/util/Time.js",
            "line": 27,
            "type": "{*}"
        },
        "Cookie": {
            "name": "Cookie",
            "submodules": {},
            "elements": {},
            "classes": {
                "Cookie": 1
            },
            "fors": {},
            "is_submodule": 1,
            "namespaces": {},
            "module": "Eda",
            "namespace": "",
            "file": "src/net/Cookie.js",
            "line": 39,
            "description": "document.cookie helper\n\nhttps://developer.mozilla.org/en-US/docs/Web/API/document.cookie\n\nthanks MDN"
        },
        "Query": {
            "name": "Query",
            "submodules": {},
            "elements": {},
            "classes": {
                "Query": 1
            },
            "fors": {},
            "is_submodule": 1,
            "namespaces": {},
            "module": "Eda",
            "namespace": "",
            "file": "src/net/Query.js",
            "line": 31,
            "description": "window.location.search utility"
        },
        "Kana": {
            "name": "Kana",
            "submodules": {},
            "elements": {},
            "classes": {
                "Kana": 1,
                "List": 1
            },
            "fors": {},
            "is_submodule": 1,
            "namespaces": {},
            "module": "Eda",
            "namespace": "",
            "file": "src/util/List.js",
            "line": 32,
            "description": "日本語判定処理"
        },
        "Num": {
            "name": "Num",
            "submodules": {},
            "elements": {},
            "classes": {
                "Num": 1
            },
            "fors": {},
            "is_submodule": 1,
            "namespaces": {},
            "module": "Eda",
            "namespace": "",
            "file": "src/util/Num.js",
            "line": 32,
            "description": "数にまつわる Utilities"
        },
        "Str": {
            "name": "Str",
            "submodules": {},
            "elements": {},
            "classes": {},
            "fors": {},
            "is_submodule": 1,
            "namespaces": {},
            "module": "Eda",
            "namespace": "",
            "file": "src/util/Str.js",
            "line": 15,
            "description": "文字 Utility"
        },
        "Time": {
            "name": "Time",
            "submodules": {},
            "elements": {},
            "classes": {
                "Time": 1
            },
            "fors": {},
            "is_submodule": 1,
            "namespaces": {},
            "module": "Eda",
            "namespace": "",
            "file": "src/util/Time.js",
            "line": 27,
            "description": "何日後, 何時間後 時間管理"
        }
    },
    "classes": {
        "Cookie": {
            "name": "Cookie",
            "shortname": "Cookie",
            "classitems": [],
            "plugins": [],
            "extensions": [],
            "plugin_for": [],
            "extension_for": [],
            "module": "Eda",
            "submodule": "Cookie",
            "namespace": "",
            "file": "src/net/Cookie.js",
            "line": 39,
            "description": "cookie utility",
            "static": 1,
            "is_constructor": 1
        },
        "Query": {
            "name": "Query",
            "shortname": "Query",
            "classitems": [],
            "plugins": [],
            "extensions": [],
            "plugin_for": [],
            "extension_for": [],
            "module": "Eda",
            "submodule": "Query",
            "namespace": "",
            "file": "src/net/Query.js",
            "line": 31,
            "is_constructor": 1
        },
        "Kana": {
            "name": "Kana",
            "shortname": "Kana",
            "classitems": [],
            "plugins": [],
            "extensions": [],
            "plugin_for": [],
            "extension_for": [],
            "module": "Eda",
            "submodule": "Kana",
            "namespace": "",
            "file": "src/util/Kana.js",
            "line": 28,
            "description": "日本語文字判定 Utility",
            "static": 1,
            "is_constructor": 1
        },
        "List": {
            "name": "List",
            "shortname": "List",
            "classitems": [],
            "plugins": [],
            "extensions": [],
            "plugin_for": [],
            "extension_for": [],
            "module": "Eda",
            "submodule": "Kana",
            "namespace": "",
            "file": "src/util/List.js",
            "line": 32,
            "description": "Array ヘルパー",
            "static": 1,
            "is_constructor": 1
        },
        "Num": {
            "name": "Num",
            "shortname": "Num",
            "classitems": [],
            "plugins": [],
            "extensions": [],
            "plugin_for": [],
            "extension_for": [],
            "module": "Eda",
            "submodule": "Num",
            "namespace": "",
            "file": "src/util/Num.js",
            "line": 32,
            "is_constructor": 1
        },
        "Time": {
            "name": "Time",
            "shortname": "Time",
            "classitems": [],
            "plugins": [],
            "extensions": [],
            "plugin_for": [],
            "extension_for": [],
            "module": "Eda",
            "submodule": "Time",
            "namespace": "",
            "file": "src/util/Time.js",
            "line": 27,
            "description": "時間管理",
            "static": 1,
            "is_constructor": 1
        }
    },
    "elements": {},
    "classitems": [
        {
            "file": "src/net/Cookie.js",
            "line": 1,
            "description": "license inazumatv.com\nauthor (at)taikiken / http://inazumatv.com\ndate 15/09/02 - 11:37\n\nCopyright (c) 2011-2015 inazumatv.com, inc.\n\nDistributed under the terms of the MIT license.\nhttp://www.opensource.org/licenses/mit-license.html\n\nThis notice shall be included in all copies or substantial portions of the Software.\n\nfor eda.js",
            "class": "Cookie"
        },
        {
            "file": "src/net/Cookie.js",
            "line": 53,
            "description": "document.cookie 取得",
            "itemtype": "method",
            "name": "item",
            "params": [
                {
                    "name": "keyName",
                    "description": "取得 cookie name",
                    "type": "String"
                }
            ],
            "return": {
                "description": "cookie 値を返します、取得できない場合は null を返します。",
                "type": "String|null"
            },
            "static": 1,
            "class": "Cookie",
            "module": "Eda",
            "submodule": "Cookie"
        },
        {
            "file": "src/net/Cookie.js",
            "line": 75,
            "description": "document.cookie 全て取得し列挙します",
            "itemtype": "method",
            "name": "all",
            "return": {
                "description": "document.cookie key name 配列を返します",
                "type": "Array"
            },
            "static": 1,
            "class": "Cookie",
            "module": "Eda",
            "submodule": "Cookie"
        },
        {
            "file": "src/net/Cookie.js",
            "line": 97,
            "description": "document.cookie 引数 keyName が存在するかを調べます",
            "itemtype": "method",
            "name": "has",
            "params": [
                {
                    "name": "keyName",
                    "description": "document.cookie 名称"
                }
            ],
            "return": {
                "description": "true / false",
                "type": "Boolean"
            },
            "static": 1,
            "class": "Cookie",
            "module": "Eda",
            "submodule": "Cookie"
        },
        {
            "file": "src/net/Cookie.js",
            "line": 119,
            "description": "document.cookie 削除",
            "itemtype": "method",
            "name": "remove",
            "params": [
                {
                    "name": "keyName",
                    "description": "document.cookie 名称",
                    "type": "String"
                },
                {
                    "name": "path",
                    "description": "document.cookie path",
                    "type": "String",
                    "optional": true
                },
                {
                    "name": "domain",
                    "description": "document.cookie domain",
                    "type": "String",
                    "optional": true
                }
            ],
            "return": {
                "description": "削除に成功したかの真偽値を返します",
                "type": "Boolean"
            },
            "static": 1,
            "class": "Cookie",
            "module": "Eda",
            "submodule": "Cookie"
        },
        {
            "file": "src/net/Cookie.js",
            "line": 144,
            "description": "document.cookie 保存",
            "itemtype": "method",
            "name": "set",
            "params": [
                {
                    "name": "keyName",
                    "description": "document.cookie 名称",
                    "type": "String"
                },
                {
                    "name": "value",
                    "description": "document.cookie value",
                    "type": "String"
                },
                {
                    "name": "end] document.cookie 期限, [ second, Date.toUTCString",
                    "description": "",
                    "type": "String|Number|Date|*",
                    "optional": true
                },
                {
                    "name": "path",
                    "description": "document.cookie path",
                    "type": "String",
                    "optional": true
                },
                {
                    "name": "domain",
                    "description": "document.cookie domain",
                    "type": "String",
                    "optional": true
                },
                {
                    "name": "secure",
                    "description": "document.cookie secure",
                    "type": "String",
                    "optional": true
                }
            ],
            "return": {
                "description": "保存に成功したかの真偽値を返します",
                "type": "Boolean"
            },
            "static": 1,
            "class": "Cookie",
            "module": "Eda",
            "submodule": "Cookie"
        },
        {
            "file": "src/net/Query.js",
            "line": 1,
            "description": "license inazumatv.com\nauthor (at)taikiken / http://inazumatv.com\ndate 15/09/01 - 17:29\n\nCopyright (c) 2011-2015 inazumatv.com, inc.\n\nDistributed under the terms of the MIT license.\nhttp://www.opensource.org/licenses/mit-license.html\n\nThis notice shall be included in all copies or substantial portions of the Software.\n\nfor eda.js",
            "class": "Query",
            "module": "Eda"
        },
        {
            "file": "src/net/Query.js",
            "line": 44,
            "itemtype": "method",
            "name": "parse",
            "params": [
                {
                    "name": "search",
                    "description": "window.location.search.substring( 1 )",
                    "type": "String=undefined",
                    "optional": true
                }
            ],
            "class": "Query",
            "module": "Eda",
            "submodule": "Query"
        },
        {
            "file": "src/net/Query.js",
            "line": 57,
            "itemtype": "method",
            "name": "find",
            "params": [
                {
                    "name": "keyName",
                    "description": "",
                    "type": "String"
                }
            ],
            "return": {
                "description": "",
                "type": "*"
            },
            "class": "Query",
            "module": "Eda",
            "submodule": "Query"
        },
        {
            "file": "src/net/Query.js",
            "line": 80,
            "itemtype": "method",
            "name": "search",
            "static": 1,
            "return": {
                "description": "",
                "type": "String"
            },
            "class": "Query",
            "module": "Eda",
            "submodule": "Query"
        },
        {
            "file": "src/net/Query.js",
            "line": 91,
            "itemtype": "method",
            "name": "parse",
            "static": 1,
            "params": [
                {
                    "name": "search",
                    "description": "window.location.search.substring( 1 )",
                    "type": "String",
                    "optional": true
                }
            ],
            "return": {
                "description": "",
                "type": "*"
            },
            "class": "Query",
            "module": "Eda",
            "submodule": "Query"
        },
        {
            "file": "src/net/Query.js",
            "line": 131,
            "description": "location.search から keyName value を返します",
            "itemtype": "method",
            "name": "find",
            "static": 1,
            "params": [
                {
                    "name": "keyName",
                    "description": "",
                    "type": "String"
                }
            ],
            "return": {
                "description": "location.search keyName value を返します",
                "type": "*"
            },
            "class": "Query",
            "module": "Eda",
            "submodule": "Query"
        },
        {
            "file": "src/util/Kana.js",
            "line": 1,
            "description": "license inazumatv.com\nauthor (at)taikiken / http://inazumatv.com\ndate 15/09/01 - 16:19\n\nCopyright (c) 2011-2015 inazumatv.com, inc.\n\nDistributed under the terms of the MIT license.\nhttp://www.opensource.org/licenses/mit-license.html\n\nThis notice shall be included in all copies or substantial portions of the Software.\n\nfor eda.js",
            "class": "Kana",
            "module": "Eda"
        },
        {
            "file": "src/util/Kana.js",
            "line": 41,
            "itemtype": "method",
            "name": "kanji",
            "static": 1,
            "params": [
                {
                    "name": "txt",
                    "description": "判定文字列",
                    "type": "String"
                }
            ],
            "return": {
                "description": "漢字かどうかの真偽値を返します",
                "type": "Boolean"
            },
            "class": "Kana",
            "module": "Eda",
            "submodule": "Kana"
        },
        {
            "file": "src/util/Kana.js",
            "line": 65,
            "itemtype": "method",
            "name": "hiragana",
            "static": 1,
            "params": [
                {
                    "name": "txt",
                    "description": "判定文字列",
                    "type": "String"
                }
            ],
            "return": {
                "description": "ひらがなか否かの真偽値を返します",
                "type": "Boolean"
            },
            "class": "Kana",
            "module": "Eda",
            "submodule": "Kana"
        },
        {
            "file": "src/util/Kana.js",
            "line": 78,
            "itemtype": "method",
            "name": "katakana",
            "static": 1,
            "params": [
                {
                    "name": "txt",
                    "description": "判定文字列",
                    "type": "String"
                }
            ],
            "return": {
                "description": "カナか否かの真偽値を返します",
                "type": "Boolean"
            },
            "class": "Kana",
            "module": "Eda",
            "submodule": "Kana"
        },
        {
            "file": "src/util/Kana.js",
            "line": 91,
            "itemtype": "method",
            "name": "hankaku",
            "static": 1,
            "params": [
                {
                    "name": "txt",
                    "description": "判定文字列",
                    "type": "String"
                }
            ],
            "return": {
                "description": "半角文字か否かの真偽値を返します",
                "type": "Boolean"
            },
            "class": "Kana",
            "module": "Eda",
            "submodule": "Kana"
        },
        {
            "file": "src/util/Kana.js",
            "line": 104,
            "itemtype": "method",
            "name": "zenkaku",
            "static": 1,
            "params": [
                {
                    "name": "txt",
                    "description": "判定文字列",
                    "type": "String"
                }
            ],
            "return": {
                "description": "全角か否かの真偽値を返します",
                "type": "Boolean"
            },
            "class": "Kana",
            "module": "Eda",
            "submodule": "Kana"
        },
        {
            "file": "src/util/Kana.js",
            "line": 117,
            "itemtype": "method",
            "name": "alphabetic",
            "static": 1,
            "params": [
                {
                    "name": "txt",
                    "description": "判定文字列",
                    "type": "String"
                }
            ],
            "return": {
                "description": "アルファベットか否かの真偽値を返します、スペースはfalseです",
                "type": "Boolean"
            },
            "class": "Kana",
            "module": "Eda",
            "submodule": "Kana"
        },
        {
            "file": "src/util/List.js",
            "line": 1,
            "description": "license inazumatv.com\nauthor (at)taikiken / http://inazumatv.com\ndate 15/09/01 - 17:14\n\nCopyright (c) 2011-2015 inazumatv.com, inc.\n\nDistributed under the terms of the MIT license.\nhttp://www.opensource.org/licenses/mit-license.html\n\nThis notice shall be included in all copies or substantial portions of the Software.\n\nfor eda.js",
            "class": "List",
            "module": "Eda"
        },
        {
            "file": "src/util/List.js",
            "line": 45,
            "description": "word で埋められた配列を length 長分作成します",
            "itemtype": "method",
            "name": "word",
            "static": 1,
            "params": [
                {
                    "name": "length",
                    "description": "",
                    "type": "Int"
                },
                {
                    "name": "word",
                    "description": "",
                    "type": "Int|string"
                }
            ],
            "return": {
                "description": "",
                "type": "Array"
            },
            "class": "List",
            "module": "Eda",
            "submodule": "Kana"
        },
        {
            "file": "src/util/List.js",
            "line": 68,
            "description": "0 で埋められた配列を length 長分作成します",
            "itemtype": "method",
            "name": "zero",
            "static": 1,
            "params": [
                {
                    "name": "length",
                    "description": "",
                    "type": "Int"
                }
            ],
            "return": {
                "description": "",
                "type": "Array"
            },
            "class": "List",
            "module": "Eda",
            "submodule": "Kana"
        },
        {
            "file": "src/util/List.js",
            "line": 84,
            "description": "配列をシャッフルします",
            "itemtype": "method",
            "name": "shuffle",
            "static": 1,
            "params": [
                {
                    "name": "array",
                    "description": "",
                    "type": "Array"
                }
            ],
            "return": {
                "description": "シャッフル後の配列を返します",
                "type": "Array"
            },
            "class": "List",
            "module": "Eda",
            "submodule": "Kana"
        },
        {
            "file": "src/util/List.js",
            "line": 118,
            "itemtype": "method",
            "name": "shuffle2",
            "static": 1,
            "params": [
                {
                    "name": "array",
                    "description": "",
                    "type": "Array"
                }
            ],
            "return": {
                "description": "シャッフル後の配列を返します",
                "type": "Array"
            },
            "class": "List",
            "module": "Eda",
            "submodule": "Kana"
        },
        {
            "file": "src/util/List.js",
            "line": 149,
            "description": "配列内の最大数値を返します\n\n配列は全て数値で無いといけません\n\n文字が含まれていると NaN を返します",
            "itemtype": "method",
            "name": "max",
            "static": 1,
            "params": [
                {
                    "name": "arr",
                    "description": "検証対象の配列、内部は全部数値 [Number, [Number]]",
                    "type": "Array"
                }
            ],
            "return": {
                "description": "配列内の最大数値を返します",
                "type": "Number"
            },
            "class": "List",
            "module": "Eda",
            "submodule": "Kana"
        },
        {
            "file": "src/util/Num.js",
            "line": 1,
            "description": "license inazumatv.com\nauthor (at)taikiken / http://inazumatv.com\ndate 15/09/01 - 16:26\n\nCopyright (c) 2011-2015 inazumatv.com, inc.\n\nDistributed under the terms of the MIT license.\nhttp://www.opensource.org/licenses/mit-license.html\n\nThis notice shall be included in all copies or substantial portions of the Software.\n\nfor eda.js",
            "class": "Num",
            "module": "Eda"
        },
        {
            "file": "src/util/Num.js",
            "line": 43,
            "description": "3桁毎にカンマ(,)を挿入します",
            "itemtype": "method",
            "name": "comma",
            "static": 1,
            "params": [
                {
                    "name": "n",
                    "description": "",
                    "type": "Number|string"
                }
            ],
            "return": {
                "description": "カンマ挿入後の文字列を返します",
                "type": "String"
            },
            "class": "Num",
            "module": "Eda",
            "submodule": "Num"
        },
        {
            "file": "src/util/Num.js",
            "line": 56,
            "description": "範囲指定乱数生成",
            "itemtype": "method",
            "name": "random",
            "static": 1,
            "params": [
                {
                    "name": "min",
                    "description": "最小値",
                    "type": "Number"
                },
                {
                    "name": "max",
                    "description": "最大値 optional",
                    "type": "Number",
                    "optional": true
                }
            ],
            "return": {
                "description": "min ~ max 間の乱数(Int)を発生させます",
                "type": "Number"
            },
            "class": "Num",
            "module": "Eda",
            "submodule": "Num"
        },
        {
            "file": "src/util/Num.js",
            "line": 84,
            "description": "数値チェック\n\n文字型でも true になる場合があります\n\n'10': true, typeof '10': string",
            "itemtype": "method",
            "name": "is",
            "static": 1,
            "params": [
                {
                    "name": "obj",
                    "description": "",
                    "type": "*"
                }
            ],
            "return": {
                "description": "true: Number, false: not Number",
                "type": "Boolean"
            },
            "class": "Num",
            "module": "Eda",
            "submodule": "Num"
        },
        {
            "file": "src/util/Str.js",
            "line": 1,
            "description": "license inazumatv.com\nauthor (at)taikiken / http://inazumatv.com\ndate 15/09/01 - 18:02\n\nCopyright (c) 2011-2015 inazumatv.com, inc.\n\nDistributed under the terms of the MIT license.\nhttp://www.opensource.org/licenses/mit-license.html\n\nThis notice shall be included in all copies or substantial portions of the Software.\n\nfor eda.js",
            "class": "Time",
            "module": "Eda"
        },
        {
            "file": "src/util/Str.js",
            "line": 40,
            "description": "文字長を検査します",
            "itemtype": "method",
            "name": "long",
            "static": 1,
            "params": [
                {
                    "name": "str",
                    "description": "検査対象文字列",
                    "type": "String"
                },
                {
                    "name": "long",
                    "description": "文字長",
                    "type": "Int"
                }
            ],
            "return": {
                "description": "文字列 length が文字長と同じかの真偽値を返します",
                "type": "Boolean"
            },
            "class": "Time",
            "module": "Eda",
            "submodule": "Str"
        },
        {
            "file": "src/util/Str.js",
            "line": 54,
            "description": "mail address validate\n\nメール形式簡易チェック",
            "itemtype": "method",
            "name": "mail",
            "params": [
                {
                    "name": "str",
                    "description": "検査対象文字列",
                    "type": "String"
                }
            ],
            "static": 1,
            "return": {
                "description": "文字列がメール形式かの真偽値を返します",
                "type": "Boolean"
            },
            "class": "Time",
            "module": "Eda",
            "submodule": "Str"
        },
        {
            "file": "src/util/Str.js",
            "line": 73,
            "itemtype": "method",
            "name": "phone",
            "params": [
                {
                    "name": "phone1",
                    "description": "市外局番",
                    "type": "String|number"
                },
                {
                    "name": "phone2",
                    "description": "市内番号",
                    "type": "String|number"
                },
                {
                    "name": "phone3",
                    "description": "識別番号",
                    "type": "String|number"
                }
            ],
            "return": {
                "description": "電話番号形式かを返します",
                "type": "Boolean"
            },
            "class": "Time",
            "module": "Eda",
            "submodule": "Str"
        },
        {
            "file": "src/util/Str.js",
            "line": 178,
            "itemtype": "method",
            "name": "zip",
            "static": 1,
            "params": [
                {
                    "name": "zip1",
                    "description": "",
                    "type": "Number|string"
                },
                {
                    "name": "zip2",
                    "description": "",
                    "type": "Number|string"
                }
            ],
            "return": {
                "description": "",
                "type": "*"
            },
            "class": "Time",
            "module": "Eda",
            "submodule": "Str"
        },
        {
            "file": "src/util/Str.js",
            "line": 222,
            "description": "改行コードを LF へ統一します",
            "itemtype": "method",
            "name": "lf",
            "static": 1,
            "params": [
                {
                    "name": "str",
                    "description": "",
                    "type": "String"
                }
            ],
            "return": {
                "description": "",
                "type": "Void|string|XML"
            },
            "class": "Time",
            "module": "Eda",
            "submodule": "Str"
        },
        {
            "file": "src/util/Str.js",
            "line": 235,
            "description": "改行コードを削除します",
            "itemtype": "method",
            "name": "removeNL",
            "static": 1,
            "params": [
                {
                    "name": "str",
                    "description": "",
                    "type": "String"
                }
            ],
            "return": {
                "description": "",
                "type": "Void|string|XML"
            },
            "class": "Time",
            "module": "Eda",
            "submodule": "Str"
        },
        {
            "file": "src/util/Str.js",
            "line": 248,
            "description": "スペースを削除します",
            "itemtype": "method",
            "name": "removeSpace",
            "static": 1,
            "params": [
                {
                    "name": "str",
                    "description": "",
                    "type": "String"
                }
            ],
            "return": {
                "description": "",
                "type": "Void|string|XML"
            },
            "class": "Time",
            "module": "Eda",
            "submodule": "Str"
        },
        {
            "file": "src/util/Str.js",
            "line": 261,
            "description": "Tabコードを削除します",
            "itemtype": "method",
            "name": "removeTab",
            "static": 1,
            "params": [
                {
                    "name": "str",
                    "description": "",
                    "type": "String"
                }
            ],
            "return": {
                "description": "",
                "type": "Void|string|XML"
            },
            "class": "Time",
            "module": "Eda",
            "submodule": "Str"
        },
        {
            "file": "src/util/Str.js",
            "line": 274,
            "description": "white space(space, tab, new line) を全て削除します",
            "itemtype": "method",
            "name": "removeWhitespace",
            "params": [
                {
                    "name": "str",
                    "description": "",
                    "type": "String"
                }
            ],
            "return": {
                "description": "",
                "type": "Void|string|XML"
            },
            "class": "Time",
            "module": "Eda",
            "submodule": "Str"
        },
        {
            "file": "src/util/Time.js",
            "line": 1,
            "description": "license inazumatv.com\nauthor (at)taikiken / http://inazumatv.com\ndate 15/09/02 - 12:30\n\nCopyright (c) 2011-2015 inazumatv.com, inc.\n\nDistributed under the terms of the MIT license.\nhttp://www.opensource.org/licenses/mit-license.html\n\nThis notice shall be included in all copies or substantial portions of the Software.\n\nfor eda.js",
            "class": "Time",
            "module": "Eda"
        },
        {
            "file": "src/util/Time.js",
            "line": 41,
            "itemtype": "property",
            "name": "SECOND",
            "final": "",
            "default": "1000",
            "type": "{number}",
            "class": "Time",
            "module": "Eda",
            "submodule": "Time"
        },
        {
            "file": "src/util/Time.js",
            "line": 47,
            "itemtype": "property",
            "name": "MINUTE",
            "final": "",
            "default": "1000 * 60",
            "type": "{number}",
            "class": "Time",
            "module": "Eda",
            "submodule": "Time"
        },
        {
            "file": "src/util/Time.js",
            "line": 53,
            "itemtype": "property",
            "name": "HOUR",
            "final": "",
            "default": "1000 * 60 * 60",
            "type": "{number}",
            "class": "Time",
            "module": "Eda",
            "submodule": "Time"
        },
        {
            "file": "src/util/Time.js",
            "line": 59,
            "itemtype": "property",
            "name": "DAY",
            "final": "",
            "default": "1000 * 60 * 60 * 24",
            "type": "{number}",
            "class": "Time",
            "module": "Eda",
            "submodule": "Time"
        },
        {
            "file": "src/util/Time.js",
            "line": 66,
            "itemtype": "method",
            "name": "hours",
            "static": 1,
            "params": [
                {
                    "name": "hour",
                    "description": "",
                    "type": "Number"
                }
            ],
            "return": {
                "description": "",
                "type": "Date"
            },
            "class": "Time",
            "module": "Eda",
            "submodule": "Time"
        },
        {
            "file": "src/util/Time.js",
            "line": 77,
            "itemtype": "method",
            "name": "days",
            "static": 1,
            "params": [
                {
                    "name": "day",
                    "description": "",
                    "type": "Number"
                }
            ],
            "return": {
                "description": "",
                "type": "Date"
            },
            "class": "Time",
            "module": "Eda",
            "submodule": "Time"
        },
        {
            "file": "src/eda.js",
            "line": 1,
            "license": "inazumatv.com",
            "author": "(at)taikiken / http://inazumatv.com",
            "date": "15/09/01 - 16:17\n\nCopyright (c) 2011-2015 inazumatv.com, inc.\n\nThis framework is released under the GNU Public License, version 3 or later.\nhttp://www.gnu.org/licenses/gpl-3.0-standalone.html\n\nversion @@version\nbuild @@buildTime\ngithub: @@url",
            "class": "",
            "module": "Eda"
        }
    ],
    "warnings": [
        {
            "message": "unknown tag: license",
            "line": " src/eda.js:1"
        },
        {
            "message": "unknown tag: date",
            "line": " src/eda.js:1"
        },
        {
            "message": "Missing item type\nlicense inazumatv.com\nauthor (at)taikiken / http://inazumatv.com\ndate 15/09/02 - 11:37\n\nCopyright (c) 2011-2015 inazumatv.com, inc.\n\nDistributed under the terms of the MIT license.\nhttp://www.opensource.org/licenses/mit-license.html\n\nThis notice shall be included in all copies or substantial portions of the Software.\n\nfor eda.js",
            "line": " src/net/Cookie.js:1"
        },
        {
            "message": "Missing item type\nlicense inazumatv.com\nauthor (at)taikiken / http://inazumatv.com\ndate 15/09/01 - 17:29\n\nCopyright (c) 2011-2015 inazumatv.com, inc.\n\nDistributed under the terms of the MIT license.\nhttp://www.opensource.org/licenses/mit-license.html\n\nThis notice shall be included in all copies or substantial portions of the Software.\n\nfor eda.js",
            "line": " src/net/Query.js:1"
        },
        {
            "message": "Missing item type\nlicense inazumatv.com\nauthor (at)taikiken / http://inazumatv.com\ndate 15/09/01 - 16:19\n\nCopyright (c) 2011-2015 inazumatv.com, inc.\n\nDistributed under the terms of the MIT license.\nhttp://www.opensource.org/licenses/mit-license.html\n\nThis notice shall be included in all copies or substantial portions of the Software.\n\nfor eda.js",
            "line": " src/util/Kana.js:1"
        },
        {
            "message": "Missing item type\nlicense inazumatv.com\nauthor (at)taikiken / http://inazumatv.com\ndate 15/09/01 - 17:14\n\nCopyright (c) 2011-2015 inazumatv.com, inc.\n\nDistributed under the terms of the MIT license.\nhttp://www.opensource.org/licenses/mit-license.html\n\nThis notice shall be included in all copies or substantial portions of the Software.\n\nfor eda.js",
            "line": " src/util/List.js:1"
        },
        {
            "message": "Missing item type\nlicense inazumatv.com\nauthor (at)taikiken / http://inazumatv.com\ndate 15/09/01 - 16:26\n\nCopyright (c) 2011-2015 inazumatv.com, inc.\n\nDistributed under the terms of the MIT license.\nhttp://www.opensource.org/licenses/mit-license.html\n\nThis notice shall be included in all copies or substantial portions of the Software.\n\nfor eda.js",
            "line": " src/util/Num.js:1"
        },
        {
            "message": "Missing item type\nlicense inazumatv.com\nauthor (at)taikiken / http://inazumatv.com\ndate 15/09/01 - 18:02\n\nCopyright (c) 2011-2015 inazumatv.com, inc.\n\nDistributed under the terms of the MIT license.\nhttp://www.opensource.org/licenses/mit-license.html\n\nThis notice shall be included in all copies or substantial portions of the Software.\n\nfor eda.js",
            "line": " src/util/Str.js:1"
        },
        {
            "message": "Missing item type\nlicense inazumatv.com\nauthor (at)taikiken / http://inazumatv.com\ndate 15/09/02 - 12:30\n\nCopyright (c) 2011-2015 inazumatv.com, inc.\n\nDistributed under the terms of the MIT license.\nhttp://www.opensource.org/licenses/mit-license.html\n\nThis notice shall be included in all copies or substantial portions of the Software.\n\nfor eda.js",
            "line": " src/util/Time.js:1"
        },
        {
            "message": "Missing item type",
            "line": " src/eda.js:1"
        }
    ]
}